.hgignore
.hgtags
CHANGES.txt
LICENSE.txt
MANIFEST.in
README.txt
bootstrap.py
buildout.cfg
setup.py
js/__init__.py
js.cropper.egg-info/PKG-INFO
js.cropper.egg-info/SOURCES.txt
js.cropper.egg-info/dependency_links.txt
js.cropper.egg-info/entry_points.txt
js.cropper.egg-info/namespace_packages.txt
js.cropper.egg-info/not-zip-safe
js.cropper.egg-info/requires.txt
js.cropper.egg-info/top_level.txt
js/cropper/__init__.py
js/cropper/test_cropper.txt
js/cropper/resources/cropper.css
js/cropper/resources/cropper.js
js/cropper/resources/cropper.min.css
js/cropper/resources/cropper.min.js