Metadata-Version: 1.0
Name: js.cropper
Version: 0.10.0-1
Summary: Fanstatic packaging of Cropper
Home-page: UNKNOWN
Author: Fanstatic Developers
Author-email: fanstatic@googlegroups.com
License: BSD
Platform: UNKNOWN
